websock-0.0.5.dist-info/DESCRIPTION.rst
websock-0.0.5.dist-info/METADATA
websock-0.0.5.dist-info/RECORD
websock-0.0.5.dist-info/WHEEL
websock-0.0.5.dist-info/metadata.json
websock-0.0.5.dist-info/top_level.txt
websocket/DataFrameFormat.py
websocket/ExampleChatServer.py
websocket/ExampleEchoServer.py
websocket/ServerException.py
websocket/WebSocketServer.py
websocket/__init__.py
