Metadata-Version: 2.0
Name: websock
Version: 0.0.5
Summary: Multithreaded websocket server following RFC 6455 protocol
Home-page: https://github.com/Kai-Bailey/websocket
Author: Kai Bailey
Author-email: kbailey1@ualberta.ca
License: MIT
Keywords: websocket client server multithreaded
Platform: UNKNOWN
